mazeforge/__init__.py
mazeforge/base.py
mazeforge/generator.py
mazeforge/maze.py
mazeforge/core/loader.py
mazeforge/core/platform/linux/aarch64/libmaze.so
mazeforge/core/platform/linux/arm/libmaze.so
mazeforge/core/platform/linux/i686/libmaze.so
mazeforge/core/platform/linux/x86_64/libmaze.so
mazeforge/core/platform/macos/arm/libmaze.dylib
mazeforge/core/platform/macos/x86_64/libmaze.dylib
mazeforge/core/platform/windows/i686/libmaze.dll
mazeforge/core/platform/windows/x86_64/libmaze.dll
mazeforge-0.2.0.dist-info/LICENSE
mazeforge-0.2.0.dist-info/METADATA
mazeforge-0.2.0.dist-info/WHEEL
mazeforge-0.2.0.dist-info/top_level.txt
mazeforge-0.2.0.dist-info/RECORD
