Metadata-Version: 2.1
Name: mazeforge
Version: 0.2.0
Summary: Simple and fast generation of mazes
Author-email: Oskar Meyenburg <oskar.meyenburg@gmail.com>
Maintainer-email: Oskar Meyenburg <oskar.meyenburg@gmail.com>
License: MIT License
Project-URL: repository, https://github.com/oskarmeyenburg/mazeforge
Project-URL: documentation, https://github.com/oskarmeyenburg/mazeforge/blob/main/README.md
Keywords: labyrinth,maze,pymaze,generation,generate,solve
Classifier: Intended Audience :: Developers
Classifier: Operating System :: MacOS :: MacOS X
Classifier: Operating System :: Microsoft :: Windows
Classifier: Operating System :: POSIX
Classifier: License :: OSI Approved :: MIT License
Classifier: Programming Language :: C
Classifier: Programming Language :: Python
Classifier: Programming Language :: Python :: 3
Requires-Python: >=3.7
License-File: LICENSE
Provides-Extra: build
Requires-Dist: build ; extra == 'build'
Requires-Dist: twine ; extra == 'build'
Provides-Extra: dev
Requires-Dist: black ; extra == 'dev'
Requires-Dist: bumpver ; extra == 'dev'
Requires-Dist: isort ; extra == 'dev'
Requires-Dist: mypy ; extra == 'dev'
Requires-Dist: pytest ; extra == 'dev'
